lines.py
setup.py
lines.egg-info/PKG-INFO
lines.egg-info/SOURCES.txt
lines.egg-info/dependency_links.txt
lines.egg-info/entry_points.txt
lines.egg-info/requires.txt
lines.egg-info/top_level.txt