Metadata-Version: 1.1
Name: lines
Version: 0.1.0-a
Summary: Treat lines of a file as elements of a set
Home-page: https://github.com/nibrahim/lines
Author: Noufal Ibrahim
Author-email: noufal@nibrahim.net.in
License: GPL
Platform: linux
Platform: osx
Platform: win32
Classifier: Development Status :: 4 - Beta
Classifier: Intended Audience :: Developers
Classifier: License :: OSI Approved :: GNU General Public License (GPL)
Classifier: Operating System :: POSIX
Classifier: Operating System :: Microsoft :: Windows
Classifier: Operating System :: MacOS :: MacOS X
Classifier: Topic :: Utilities
Classifier: Programming Language :: Python
